sdqc/__init__.py
sdqc/_version.py
sdqc/checks.py
sdqc/checks_dict.py
sdqc/default-conf.ini
sdqc/default-report-conf.json
sdqc/loading.py
sdqc/loading_examples.py
sdqc/main.py
sdqc/reports.py
sdqc/tools.py
sdqc-0.5.0.dist-info/LICENSE
sdqc-0.5.0.dist-info/METADATA
sdqc-0.5.0.dist-info/WHEEL
sdqc-0.5.0.dist-info/top_level.txt
sdqc-0.5.0.dist-info/RECORD
