Metadata-Version: 2.1
Name: sdqc
Version: 0.5.0
Summary: System Dynamics Data Quality Check with Python
Home-page: https://gitlab.com/eneko.martin.martinez/sdqc
Author: Eneko Martin Martinez
Author-email: eneko.martin.martinez@gmail.com
License: MIT
Keywords: System Dynamics,Vensim,Quality Check
Platform: UNKNOWN
Classifier: Development Status :: 3 - Alpha
Classifier: Topic :: Scientific/Engineering :: Information Analysis
Classifier: Intended Audience :: Science/Research
Classifier: License :: OSI Approved :: MIT License
Classifier: Programming Language :: Python :: 3.7
Classifier: Programming Language :: Python :: 3.8
Classifier: Programming Language :: Python :: 3.9
Classifier: Programming Language :: Python :: 3.10
Requires-Python: >=3.7
Requires-Dist: pypandoc
Requires-Dist: pysd (>=3.8)
Requires-Dist: netCDF4 (==1.6) ; platform_system != "Windows" or python_version != "3.7"
Requires-Dist: netCDF4 (==1.5) ; platform_system == "Windows" and python_version == "3.7"
Requires-Dist: importlib-metadata (==2.0) ; python_version == "3.7"
